setup.py
distributionsAbhi/Binomialdistribution.py
distributionsAbhi/Gaussiandistribution.py
distributionsAbhi/Generaldistribution.py
distributionsAbhi/__init__.py
distributionsAbhi.egg-info/PKG-INFO
distributionsAbhi.egg-info/SOURCES.txt
distributionsAbhi.egg-info/dependency_links.txt
distributionsAbhi.egg-info/not-zip-safe
distributionsAbhi.egg-info/top_level.txt